manage.py
r_shepard/__init__.py
r_shepard/api/__init__.py
r_shepard/api/admin.py
r_shepard/api/apps.py
r_shepard/api/migrations/0001_initial.py
r_shepard/api/migrations/0002_project_is_active.py
r_shepard/api/migrations/0003_project_url.py
r_shepard/api/migrations/0004_project_rstudio_version.py
r_shepard/api/migrations/0005_remove_project_url_project_local_url_and_more.py
r_shepard/api/migrations/0006_remove_project_cpus_remove_project_is_active_and_more.py
r_shepard/api/migrations/0007_alter_container_container_id.py
r_shepard/api/migrations/0008_container_port_alter_container_container_id_and_more.py
r_shepard/api/migrations/0009_alter_container_port.py
r_shepard/api/migrations/0010_alter_container_port.py
r_shepard/api/migrations/0011_alter_container_tailscale_serve_url.py
r_shepard/api/migrations/0012_project_slug.py
r_shepard/api/migrations/0013_remove_project_password_container_password.py
r_shepard/api/migrations/0014_project_max_containers.py
r_shepard/api/migrations/0015_project_auto_commit_enabled_project_git_repo_url.py
r_shepard/api/migrations/0016_project_commit_interval_project_last_commit_time_and_more.py
r_shepard/api/migrations/0017_alter_container_container_id_alter_container_cpus_and_more.py
r_shepard/api/migrations/0018_project_description.py
r_shepard/api/migrations/0019_alter_project_commit_interval_and_more.py
r_shepard/api/migrations/0020_alter_container_port.py
r_shepard/api/migrations/0021_remove_container_tailscale_funnel_url_and_more.py
r_shepard/api/migrations/0022_container_image_host_alter_project_git_repo_url.py
r_shepard/api/migrations/0023_remove_container_cpus_remove_project_max_containers_and_more.py
r_shepard/api/migrations/0024_container_username.py
r_shepard/api/migrations/__init__.py
r_shepard/api/models.py
r_shepard/api/podman.py
r_shepard/api/static/custom.css
r_shepard/api/static/ext/loading-states.js
r_shepard/api/static/favicon.ico
r_shepard/api/static/htmx.min.js
r_shepard/api/static/pico.blue.min.css
r_shepard-0.3.24.dist-info/METADATA
r_shepard-0.3.24.dist-info/WHEEL
r_shepard-0.3.24.dist-info/entry_points.txt
r_shepard-0.3.24.dist-info/RECORD
