Metadata-Version: 2.1
Name: r-shepard
Version: 0.3.24
Summary: 
License: GPL-3.0
Author: linozen
Author-email: linus@sehn.dev
Requires-Python: >=3.10,<4.0
Classifier: License :: OSI Approved :: GNU General Public License v3 (GPLv3)
Classifier: Programming Language :: Python :: 3
Classifier: Programming Language :: Python :: 3.10
Classifier: Programming Language :: Python :: 3.11
Classifier: Programming Language :: Python :: 3.12
Requires-Dist: celery (>=5.4.0,<6.0.0)
Requires-Dist: daphne (>=4.1.2,<5.0.0)
Requires-Dist: django (>=5.0.4,<6.0.0)
Requires-Dist: django-admin-interface (>=0.28.6,<0.29.0)
Requires-Dist: django-otp-yubikey (>=1.1.0,<2.0.0)
Requires-Dist: django-two-factor-auth (>=1.16.0,<2.0.0)
Requires-Dist: phonenumberslite (>=8.13.35,<9.0.0)
Requires-Dist: podman (>=5.0.0,<6.0.0)
Requires-Dist: redis (>=5.0.4,<6.0.0)
